[
    {
      "shopid": "134790807",
      "productid": "13045241703",
      "name": "[ Thanh Lý] Ð?ng H? Thông Minh Apple Watch Series 4 40mm Space Gray Aluminium Black Sport Loop (GPS)",
      "price": "6000000",
      "discount": "",
      "rate": "0",
      "ratecount": "0",
      "sold": "0",
      "instock": "1",
      "location": "TP. H? Chí Minh",
      "mall": "Shopee",
      "link": "https://shopee.vn/[ Thanh Lý] Ð?ng H? Thông Minh Apple Watch Series 4 40mm Space Gray Aluminium Black Sport Loop (GPS)-i.134790807.13045241703",
      "Color-split": "BLACK",
      "Model-split": "APPLE WATCH SERIES 4"
    },
    {
      "shopid": "88201679",
      "productid": "13281441802",
      "name": "[Mã ELAP1TR gi?m 5% don 3TR] Apple Watch SE 44mm GPS + Cellular Sport Loop",
      "price": "7990000",
      "discount": "33%",
      "rate": "5",
      "ratecount": "4",
      "sold": "14",
      "instock": "3",
      "location": "Hà N?i",
      "mall": "Shopee",
      "link": "https://shopee.vn/[Mã ELAP1TR gi?m 5% don 3TR] Apple Watch SE 44mm GPS + Cellular Sport Loop-i.88201679.13281441802",
      "Model-split": "APPLE WATCH SE"
    },
    {
      "shopid": "88201679",
      "productid": "13281441802",
      "name": "[Mã ELAP1TR gi?m 5% don 3TR] Apple Watch SE 44mm GPS + Cellular Sport Loop",
      "price": "7990000",
      "discount": "33%",
      "rate": "5",
      "ratecount": "4",
      "sold": "14",
      "instock": "3",
      "location": "Hà N?i",
      "mall": "Shopee",
      "link": "https://shopee.vn/[Mã ELAP1TR gi?m 5% don 3TR] Apple Watch SE 44mm GPS + Cellular Sport Loop-i.88201679.13281441802",
      "Model-split": "APPLE WATCH SE"
    },
    {
      "shopid": "88201679",
      "productid": "6446665760",
      "name": "[Mã ELAP1TR gi?m 5% don 3TR] Apple Watch Series 3 38mm GPS Sport Band",
      "price": "4590000",
      "discount": "40%",
      "rate": "4.9",
      "ratecount": "274",
      "sold": "677",
      "instock": "1",
      "location": "Hà N?i",
      "mall": "Shopee",
      "link": "https://shopee.vn/[Mã ELAP1TR gi?m 5% don 3TR] Apple Watch Series 3 38mm GPS Sport Band-i.88201679.6446665760",
      "Model-split": "APPLE WATCH SERIES 3"
    },
    {
      "shopid": "88201679",
      "productid": "6257515197",
      "name": "[Mã ELAP1TR gi?m 5% don 3TR] Apple Watch Series 6 40mm GPS Sport Band",
      "price": "8590000",
      "discount": "34%",
      "rate": "4.8",
      "ratecount": "173",
      "sold": "478",
      "instock": "14",
      "location": "TP. H? Chí Minh",
      "mall": "Shopee",
      "link": "https://shopee.vn/[Mã ELAP1TR gi?m 5% don 3TR] Apple Watch Series 6 40mm GPS Sport Band-i.88201679.6257515197",
      "Model-split": "APPLE WATCH SERIES 6"
    },
    {
      "shopid": "88201679",
      "productid": "12242066962",
      "name": "[Mã ELAP1TR gi?m 5% don 3TR] Apple Watch Series 7 41mm GPS Sport Band",
      "price": "9990000",
      "discount": "17%",
      "rate": "4.8",
      "ratecount": "44",
      "sold": "125",
      "instock": "14",
      "location": "TP. H? Chí Minh",
      "mall": "Shopee",
      "link": "https://shopee.vn/[Mã ELAP1TR gi?m 5% don 3TR] Apple Watch Series 7 41mm GPS Sport Band-i.88201679.12242066962",
      "Model-split": "APPLE WATCH SE"
    },
    {
      "shopid": "88201679",
      "productid": "13442053021",
      "name": "[Mã ELAP1TR gi?m 5% don 3TR] Apple Watch Series 7 45mm GPS Sport Band",
      "price": "10590000",
      "discount": "18%",
      "rate": "4.6",
      "ratecount": "16",
      "sold": "49",
      "instock": "3",
      "location": "TP. H? Chí Minh",
      "mall": "Shopee",
      "link": "https://shopee.vn/[Mã ELAP1TR gi?m 5% don 3TR] Apple Watch Series 7 45mm GPS Sport Band-i.88201679.13442053021",
      "Model-split": "APPLE WATCH SE"
    },
    {
      "shopid": "92532150",
      "productid": "14569836975",
      "name": "[Tr? góp 0%] Ð?ng h? thông minh Apple Watch Series 6 AL GPS + Cellular 44mm- Hàng Chính Hãng [Futureworld- APR]",
      "price": "10790000",
      "discount": "17%",
      "rate": "0",
      "ratecount": "0",
      "sold": "0",
      "instock": "2",
      "location": "TP. H? Chí Minh",
      "mall": "Shopee",
      "link": "https://shopee.vn/[Tr? góp 0%] Ð?ng h? thông minh Apple Watch Series 6 AL GPS + Cellular 44mm- Hàng Chính Hãng [Futureworld- APR]-i.92532150.14569836975",
      "Color-split": "Ð?NG",
      "Model-split": "APPLE WATCH SERIES 6"
    },
    {
      "shopid": "92532150",
      "productid": "13753220491",
      "name": "[Tr? góp 0%] Ð?ng h? thông minh Apple Watch Series 7 AL GPS 45mm- Hàng Chính Hãng [Futureworld- APR]",
      "price": "10741000",
      "discount": "17%",
      "rate": "5",
      "ratecount": "1",
      "sold": "1",
      "instock": "5",
      "location": "TP. H? Chí Minh",
      "mall": "Shopee",
      "link": "https://shopee.vn/[Tr? góp 0%] Ð?ng h? thông minh Apple Watch Series 7 AL GPS 45mm- Hàng Chính Hãng [Futureworld- APR]-i.92532150.13753220491",
      "Color-split": "Ð?NG",
      "Model-split": "APPLE WATCH SE"
    },
    {
      "shopid": "445492105",
      "productid": "11674962946",
      "name": "APPLE WATCH",
      "price": "3000000",
      "discount": "",
      "rate": "0",
      "ratecount": "0",
      "sold": "0",
      "instock": "1",
      "location": "Ð?ng Nai",
      "mall": "Shopee",
      "link": "https://shopee.vn/APPLE WATCH-i.445492105.11674962946"
    },
    {
      "shopid": "281671154",
      "productid": "15083779454",
      "name": "apple watch 5 c?a nho",
      "price": "4000000",
      "discount": "",
      "rate": "0",
      "ratecount": "0",
      "sold": "0",
      "instock": "705",
      "location": "Ð?ng Nai",
      "mall": "Shopee",
      "link": "https://shopee.vn/apple watch 5 c?a nho-i.281671154.15083779454"
    },
    {
      "shopid": "593817708",
      "productid": "15701313979",
      "name": "apple watch cu c?a tôi",
      "price": "3500000",
      "discount": "",
      "rate": "0",
      "ratecount": "0",
      "sold": "0",
      "instock": "10",
      "location": "Ðà N?ng",
      "mall": "Shopee",
      "link": "https://shopee.vn/apple watch cu c?a tôi-i.593817708.15701313979"
    },
    {
      "shopid": "52623865",
      "productid": "13641664275",
      "name": "Apple Watch chính hãng series 4 Thép 40mm 44mm m?i 99% 1d?i1",
      "price": "7590000",
      "discount": "",
      "rate": "0",
      "ratecount": "0",
      "sold": "0",
      "instock": "240",
      "location": "Ðà N?ng",
      "mall": "Shopee",
      "link": "https://shopee.vn/Apple Watch chính hãng series 4 Thép 40mm 44mm m?i 99% 1d?i1-i.52623865.13641664275",
      "Status-split": "99%"
    },
    {
      "shopid": "487028617",
      "productid": "15313163199",
      "name": "Apple Watch S7 LTE 41mm - Chính Hãng VN/A",
      "price": "16990000",
      "discount": "",
      "rate": "0",
      "ratecount": "0",
      "sold": "0",
      "instock": "12",
      "location": "TP. H? Chí Minh",
      "mall": "Shopee",
      "link": "https://shopee.vn/Apple Watch S7 LTE 41mm - Chính Hãng VN/A-i.487028617.15313163199"
    },
    {
      "shopid": "288286284",
      "productid": "20401734640",
      "name": "Apple Watch SE (2022) GPS + Cellular Sport Loop (Dây v?i)",
      "price": "8190000",
      "discount": "18%",
      "rate": "0",
      "ratecount": "0",
      "sold": "0",
      "instock": "25",
      "location": "TP. H? Chí Minh",
      "mall": "Shopee",
      "link": "https://shopee.vn/Apple Watch SE (2022) GPS + Cellular Sport Loop (Dây v?i)-i.288286284.20401734640",
      "Model-split": "APPLE WATCH SE"
    },
    {
      "shopid": "288286284",
      "productid": "19001749197",
      "name": "Apple Watch SE (2022) GPS Sport Band (Dây cao su)",
      "price": "7290000",
      "discount": "19%",
      "rate": "0",
      "ratecount": "0",
      "sold": "3",
      "instock": "105",
      "location": "TP. H? Chí Minh",
      "mall": "Shopee",
      "link": "https://shopee.vn/Apple Watch SE (2022) GPS Sport Band (Dây cao su)-i.288286284.19001749197",
      "Model-split": "APPLE WATCH SE"
    },
    {
      "shopid": "288286284",
      "productid": "3958124529",
      "name": "Apple Watch SE (GPS + Cellular) Dây Cao Su",
      "price": "7990000",
      "discount": "40%",
      "rate": "0",
      "ratecount": "0",
      "sold": "1",
      "instock": "40",
      "location": "TP. H? Chí Minh",
      "mall": "Shopee",
      "link": "https://shopee.vn/Apple Watch SE (GPS + Cellular) Dây Cao Su-i.288286284.3958124529",
      "Model-split": "APPLE WATCH SE"
    },
    {
      "shopid": "36740902",
      "productid": "15566092976",
      "name": "Apple Watch SE 40 den GPS mã VN/A",
      "price": "5300000",
      "discount": "",
      "rate": "0",
      "ratecount": "0",
      "sold": "0",
      "instock": "1",
      "location": "TP. H? Chí Minh",
      "mall": "Shopee",
      "link": "https://shopee.vn/Apple Watch SE 40 den GPS mã VN/A-i.36740902.15566092976",
      "Color-split": "ÐEN",
      "Model-split": "APPLE WATCH SE"
    },
    {
      "shopid": "627563397",
      "productid": "15733793239",
      "name": "Apple Watch SE 40mm GPS Sport Band Chính Hãng VN/A - B?o Hành 12 Tháng",
      "price": "8990000",
      "discount": "",
      "rate": "0",
      "ratecount": "0",
      "sold": "0",
      "instock": "7",
      "location": "B?c Ninh",
      "mall": "Shopee",
      "link": "https://shopee.vn/Apple Watch SE 40mm GPS Sport Band Chính Hãng VN/A - B?o Hành 12 Tháng-i.627563397.15733793239",
      "Model-split": "APPLE WATCH SE"
    },
    {
      "shopid": "39470545",
      "productid": "14728914105",
      "name": "Apple Watch SE 40mm LTE LL/A Sport Loop",
      "price": "5550000",
      "discount": "",
      "rate": "0",
      "ratecount": "0",
      "sold": "0",
      "instock": "15",
      "location": "Ðà N?ng",
      "mall": "Shopee",
      "link": "https://shopee.vn/Apple Watch SE 40mm LTE LL/A Sport Loop-i.39470545.14728914105",
      "Model-split": "APPLE WATCH SE"
    },
    {
      "shopid": "39470545",
      "productid": "12465558414",
      "name": "Apple Watch SE 44mm LTE LL/A Sport Loop",
      "price": "6250000",
      "discount": "",
      "rate": "0",
      "ratecount": "0",
      "sold": "0",
      "instock": "5",
      "location": "Ðà N?ng",
      "mall": "Shopee",
      "link": "https://shopee.vn/Apple Watch SE 44mm LTE LL/A Sport Loop-i.39470545.12465558414",
      "Model-split": "APPLE WATCH SE"
    },
    {
      "shopid": "288286284",
      "productid": "9044540732",
      "name": "Apple Watch Series 3 (GPS)",
      "price": "4970000",
      "discount": "19%",
      "rate": "5",
      "ratecount": "12",
      "sold": "37",
      "instock": "356",
      "location": "TP. H? Chí Minh",
      "mall": "Shopee",
      "link": "https://shopee.vn/Apple Watch Series 3 (GPS)-i.288286284.9044540732",
      "Model-split": "APPLE WATCH SERIES 3"
    },
    {
      "shopid": "627563397",
      "productid": "14833812645",
      "name": "Apple Watch Series 3 (GPS) >",
      "price": "6150000",
      "discount": "",
      "rate": "0",
      "ratecount": "0",
      "sold": "0",
      "instock": "41",
      "location": "B?c Ninh",
      "mall": "Shopee",
      "link": "https://shopee.vn/Apple Watch Series 3 (GPS) >-i.627563397.14833812645",
      "Model-split": "APPLE WATCH SERIES 3"
    },
    {
      "shopid": "762894395",
      "productid": "10194856969",
      "name": "Apple watch Series 6 ( GPS )",
      "price": "7000000",
      "discount": "",
      "rate": "0",
      "ratecount": "0",
      "sold": "0",
      "instock": "200",
      "location": "Nam Ð?nh",
      "mall": "Shopee",
      "link": "https://shopee.vn/Apple watch Series 6 ( GPS )-i.762894395.10194856969",
      "Model-split": "APPLE WATCH SERIES 6"
    },
    {
      "shopid": "288286284",
      "productid": "7658029332",
      "name": "Apple Watch Series 6 (GPS + Cellular) Stainless Steel (Thép không g?/ Dây Milanese)",
      "price": "17690000",
      "discount": "38%",
      "rate": "0",
      "ratecount": "0",
      "sold": "0",
      "instock": "8",
      "location": "TP. H? Chí Minh",
      "mall": "Shopee",
      "link": "https://shopee.vn/Apple Watch Series 6 (GPS + Cellular) Stainless Steel (Thép không g?/ Dây Milanese)-i.288286284.7658029332",
      "Model-split": "APPLE WATCH SERIES 6"
    },
    {
      "shopid": "627563397",
      "productid": "13667917153",
      "name": "Apple Watch Series 6 (GPS + Cellular) Stainless Steel (Thép không g?/ Dây Milanese) >",
      "price": "26990000",
      "discount": "",
      "rate": "0",
      "ratecount": "0",
      "sold": "0",
      "instock": "11",
      "location": "B?c Ninh",
      "mall": "Shopee",
      "link": "https://shopee.vn/Apple Watch Series 6 (GPS + Cellular) Stainless Steel (Thép không g?/ Dây Milanese) >-i.627563397.13667917153",
      "Model-split": "APPLE WATCH SERIES 6"
    },
    {
      "shopid": "627563397",
      "productid": "13867895333",
      "name": "Apple Watch Series 6 40mm GPS Sport Band Chính Hãng VN/A - B?o Hành 12 Tháng",
      "price": "12990000",
      "discount": "",
      "rate": "0",
      "ratecount": "0",
      "sold": "0",
      "instock": "16",
      "location": "B?c Ninh",
      "mall": "Shopee",
      "link": "https://shopee.vn/Apple Watch Series 6 40mm GPS Sport Band Chính Hãng VN/A - B?o Hành 12 Tháng-i.627563397.13867895333",
      "Model-split": "APPLE WATCH SERIES 6"
    },
    {
      "shopid": "288286284",
      "productid": "5757565830",
      "name": "Apple Watch Series 6 GPS Sport Band (Dây Cao Su)",
      "price": "9290000",
      "discount": "35%",
      "rate": "4.7",
      "ratecount": "22",
      "sold": "79",
      "instock": "75",
      "location": "TP. H? Chí Minh",
      "mall": "Shopee",
      "link": "https://shopee.vn/Apple Watch Series 6 GPS Sport Band (Dây Cao Su)-i.288286284.5757565830",
      "Model-split": "APPLE WATCH SERIES 6"
    },
    {
      "shopid": "92532150",
      "productid": "14703407975",
      "name": "Apple Watch Series 7 41mm (GPS)",
      "price": "9940000",
      "discount": "17%",
      "rate": "0",
      "ratecount": "0",
      "sold": "0",
      "instock": "4",
      "location": "TP. H? Chí Minh",
      "mall": "Shopee",
      "link": "https://shopee.vn/Apple Watch Series 7 41mm (GPS)-i.92532150.14703407975",
      "Model-split": "APPLE WATCH SE"
    },
    {
      "shopid": "92532150",
      "productid": "12653242867",
      "name": "Apple Watch series 7 41mm GPS +CELL",
      "price": "12614000",
      "discount": "16%",
      "rate": "0",
      "ratecount": "0",
      "sold": "0",
      "instock": "5",
      "location": "TP. H? Chí Minh",
      "mall": "Shopee",
      "link": "https://shopee.vn/Apple Watch series 7 41mm GPS +CELL-i.92532150.12653242867",
      "Model-split": "APPLE WATCH SE"
    },
    {
      "shopid": "288286284",
      "productid": "11075586393",
      "name": "Apple Watch Series 7 Nhôm (GPS+ Cellular) Dây Th? Thao",
      "price": "13250000",
      "discount": "19%",
      "rate": "5",
      "ratecount": "1",
      "sold": "4",
      "instock": "65",
      "location": "TP. H? Chí Minh",
      "mall": "Shopee",
      "link": "https://shopee.vn/Apple Watch Series 7 Nhôm (GPS+ Cellular) Dây Th? Thao-i.288286284.11075586393",
      "Model-split": "APPLE WATCH SE"
    },
    {
      "shopid": "627563397",
      "productid": "14833799440",
      "name": "Apple Watch Series 7 Nhôm (GPS+ Cellular) Dây Th? Thao Chính Hãng VN/A - B?o Hành 12 Tháng",
      "price": "15990000",
      "discount": "",
      "rate": "0",
      "ratecount": "0",
      "sold": "0",
      "instock": "32",
      "location": "B?c Ninh",
      "mall": "Shopee",
      "link": "https://shopee.vn/Apple Watch Series 7 Nhôm (GPS+ Cellular) Dây Th? Thao Chính Hãng VN/A - B?o Hành 12 Tháng-i.627563397.14833799440",
      "Model-split": "APPLE WATCH SE"
    },
    {
      "shopid": "627563397",
      "productid": "12867918191",
      "name": "Apple Watch Series 7 Thép (GPS+ Cellular) Dây Thép Chính Hãng VN/A - B?o Hành 12 Tháng",
      "price": "21990000",
      "discount": "",
      "rate": "0",
      "ratecount": "0",
      "sold": "0",
      "instock": "8",
      "location": "B?c Ninh",
      "mall": "Shopee",
      "link": "https://shopee.vn/Apple Watch Series 7 Thép (GPS+ Cellular) Dây Thép Chính Hãng VN/A - B?o Hành 12 Tháng-i.627563397.12867918191",
      "Model-split": "APPLE WATCH SE"
    },
    {
      "shopid": "91876027",
      "productid": "15209920906",
      "name": "Case apple watch",
      "price": "6000000",
      "discount": "",
      "rate": "0",
      "ratecount": "0",
      "sold": "0",
      "instock": "797979",
      "location": "Qu?ng Ngãi",
      "mall": "Shopee",
      "link": "https://shopee.vn/Case apple watch-i.91876027.15209920906"
    },
    {
      "shopid": "113278743",
      "productid": "15864476081",
      "name": "Case Apple Watch Anh Qu?c chính hãng",
      "price": "4400000",
      "discount": "20%",
      "rate": "0",
      "ratecount": "0",
      "sold": "0",
      "instock": "60",
      "location": "Hà N?i",
      "mall": "Shopee",
      "link": "https://shopee.vn/Case Apple Watch Anh Qu?c chính hãng-i.113278743.15864476081"
    },
    {
      "shopid": "152168641",
      "productid": "10689209762",
      "name": "d/h? táo Watch SE GPS + Cellular 44mm MYF02VN/A Space Gray Aluminium ?p with Black Sport Band cu",
      "price": "5225000",
      "discount": "5%",
      "rate": "0",
      "ratecount": "0",
      "sold": "0",
      "instock": "1",
      "location": "TP. H? Chí Minh",
      "mall": "Shopee",
      "link": "https://shopee.vn/d/h? táo Watch SE GPS + Cellular 44mm MYF02VN/A Space Gray Aluminium ?p with Black Sport Band cu-i.152168641.10689209762",
      "Color-split": "BLACK"
    },
    {
      "shopid": "545645339",
      "productid": "13640887395",
      "name": "Ð?ng h? Apple SE 40mm b?n nhôm  Gps fulbox",
      "price": "6700000",
      "discount": "",
      "rate": "0",
      "ratecount": "0",
      "sold": "0",
      "instock": "6",
      "location": "Thái Nguyên",
      "mall": "Shopee",
      "link": "https://shopee.vn/Ð?ng h? Apple SE 40mm b?n nhôm  Gps fulbox-i.545645339.13640887395",
      "Color-split": "Ð?NG",
      "Model-split": "APPLE SE"
    },
    {
      "shopid": "545645339",
      "productid": "13240893444",
      "name": "Ð?ng h? Apple SE size 44mm nhôm den Gps ( New Active )",
      "price": "6900000",
      "discount": "",
      "rate": "0",
      "ratecount": "0",
      "sold": "0",
      "instock": "1",
      "location": "Thái Nguyên",
      "mall": "Shopee",
      "link": "https://shopee.vn/Ð?ng h? Apple SE size 44mm nhôm den Gps ( New Active )-i.545645339.13240893444",
      "Color-split": "Ð?NG",
      "Model-split": "APPLE SE"
    },
    {
      "shopid": "545645339",
      "productid": "15015685488",
      "name": "Ð?ng h? Apple Series 3 b?n nhôm tr?ng GPS",
      "price": "3600000",
      "discount": "",
      "rate": "0",
      "ratecount": "0",
      "sold": "0",
      "instock": "1",
      "location": "Thái Nguyên",
      "mall": "Shopee",
      "link": "https://shopee.vn/Ð?ng h? Apple Series 3 b?n nhôm tr?ng GPS-i.545645339.15015685488",
      "Color-split": "Ð?NG",
      "Model-split": "APPLE SE"
    },
    {
      "shopid": "545645339",
      "productid": "13148480442",
      "name": "Ð?ng h? Apple series 3 size 38 b?n lte nhôm h?ng",
      "price": "3800000",
      "discount": "",
      "rate": "0",
      "ratecount": "0",
      "sold": "0",
      "instock": "2",
      "location": "Thái Nguyên",
      "mall": "Shopee",
      "link": "https://shopee.vn/Ð?ng h? Apple series 3 size 38 b?n lte nhôm h?ng-i.545645339.13148480442",
      "Color-split": "Ð?NG",
      "Model-split": "APPLE SE"
    },
    {
      "shopid": "545645339",
      "productid": "12440912593",
      "name": "Ð?ng h? Apple series 3 size 38mm b?n nhôm den GPS",
      "price": "4000000",
      "discount": "",
      "rate": "0",
      "ratecount": "0",
      "sold": "0",
      "instock": "1",
      "location": "Thái Nguyên",
      "mall": "Shopee",
      "link": "https://shopee.vn/Ð?ng h? Apple series 3 size 38mm b?n nhôm den GPS-i.545645339.12440912593",
      "Color-split": "Ð?NG",
      "Model-split": "APPLE SE"
    },
    {
      "shopid": "545645339",
      "productid": "13740885244",
      "name": "Ð?ng h? Apple series 4 size 40mm b?n nhôm den",
      "price": "5100000",
      "discount": "",
      "rate": "0",
      "ratecount": "0",
      "sold": "0",
      "instock": "2",
      "location": "Thái Nguyên",
      "mall": "Shopee",
      "link": "https://shopee.vn/Ð?ng h? Apple series 4 size 40mm b?n nhôm den-i.545645339.13740885244",
      "Color-split": "Ð?NG",
      "Model-split": "APPLE SE"
    },
    {
      "shopid": "55425105",
      "productid": "18701144576",
      "name": "Ð?ng h? apple w SE",
      "price": "5500000",
      "discount": "",
      "rate": "0",
      "ratecount": "0",
      "sold": "0",
      "instock": "0",
      "location": "Hà N?i",
      "mall": "Shopee",
      "link": "https://shopee.vn/Ð?ng h? apple w SE-i.55425105.18701144576",
      "Color-split": "Ð?NG"
    },
    {
      "shopid": "55425105",
      "productid": "18701144576",
      "name": "Ð?ng h? apple w SE",
      "price": "5500000",
      "discount": "",
      "rate": "0",
      "ratecount": "0",
      "sold": "0",
      "instock": "0",
      "location": "Hà N?i",
      "mall": "Shopee",
      "link": "https://shopee.vn/Ð?ng h? apple w SE-i.55425105.18701144576",
      "Color-split": "Ð?NG"
    },
    {
      "shopid": "464758802",
      "productid": "12418905521",
      "name": "Ð?NG H? APPLE WATCH SE GPS 40MM ALUMINUM CASE WITH SPORT BAND M?T NHÔM DÂY CAO SU",
      "price": "7300000",
      "discount": "",
      "rate": "0",
      "ratecount": "0",
      "sold": "0",
      "instock": "30",
      "location": "TP. H? Chí Minh",
      "mall": "Shopee",
      "link": "https://shopee.vn/Ð?NG H? APPLE WATCH SE GPS 40MM ALUMINUM CASE WITH SPORT BAND M?T NHÔM DÂY CAO SU-i.464758802.12418905521",
      "Color-split": "Ð?NG",
      "Model-split": "APPLE WATCH SE"
    },
    {
      "shopid": "45588198",
      "productid": "16621418158",
      "name": "Ð?ng H? Apple Watch series 3 LTE 99%",
      "price": "7500000",
      "discount": "",
      "rate": "0",
      "ratecount": "0",
      "sold": "0",
      "instock": "20",
      "location": "Hà N?i",
      "mall": "Shopee",
      "link": "https://shopee.vn/Ð?ng H? Apple Watch series 3 LTE 99%-i.45588198.16621418158",
      "Color-split": "Ð?NG",
      "Model-split": "APPLE WATCH SERIES 3",
      "Status-split": "99%"
    },
    {
      "shopid": "40879914",
      "productid": "15064930599",
      "name": "Ð?ng h? thông minh Apple Hermes S5 44mm BLACK(dã qua s? d?ng)",
      "price": "13000000",
      "discount": "",
      "rate": "0",
      "ratecount": "0",
      "sold": "0",
      "instock": "1",
      "location": "Ð?ng Nai",
      "mall": "Shopee",
      "link": "https://shopee.vn/Ð?ng h? thông minh Apple Hermes S5 44mm BLACK(dã qua s? d?ng)-i.40879914.15064930599",
      "Color-split": "BLACK"
    },
    {
      "shopid": "63397862",
      "productid": "12538454438",
      "name": "d?ng h? thông minh Apple seri5",
      "price": "4000000",
      "discount": "",
      "rate": "0",
      "ratecount": "0",
      "sold": "0",
      "instock": "10",
      "location": "Hà N?i",
      "mall": "Shopee",
      "link": "https://shopee.vn/d?ng h? thông minh Apple seri5-i.63397862.12538454438",
      "Color-split": "Ð?NG",
      "Model-split": "APPLE SE"
    },
    {
      "shopid": "127543801",
      "productid": "10914896174",
      "name": "Ð?ng H? Thông Minh Apple Watch S3",
      "price": "3100000",
      "discount": "",
      "rate": "0",
      "ratecount": "0",
      "sold": "0",
      "instock": "35",
      "location": "TP. H? Chí Minh",
      "mall": "Shopee",
      "link": "https://shopee.vn/Ð?ng H? Thông Minh Apple Watch S3-i.127543801.10914896174",
      "Color-split": "Ð?NG"
    },
    {
      "shopid": "127543801",
      "productid": "10914896174",
      "name": "Ð?ng H? Thông Minh Apple Watch S3",
      "price": "3100000",
      "discount": "",
      "rate": "0",
      "ratecount": "0",
      "sold": "0",
      "instock": "35",
      "location": "TP. H? Chí Minh",
      "mall": "Shopee",
      "link": "https://shopee.vn/Ð?ng H? Thông Minh Apple Watch S3-i.127543801.10914896174",
      "Color-split": "Ð?NG"
    },
    {
      "shopid": "331695868",
      "productid": "6466373717",
      "name": "Ð?ng h? thông minh Apple Watch Series 3 GPS Aluminum Case Sport Band - Hàng chính hãng",
      "price": "4489000",
      "discount": "25%",
      "rate": "0",
      "ratecount": "0",
      "sold": "2",
      "instock": "2",
      "location": "B?n Tre",
      "mall": "Shopee",
      "link": "https://shopee.vn/Ð?ng h? thông minh Apple Watch Series 3 GPS Aluminum Case Sport Band - Hàng chính hãng-i.331695868.6466373717",
      "Color-split": "Ð?NG",
      "Model-split": "APPLE WATCH SERIES 3"
    },
    {
      "shopid": "627563397",
      "productid": "15729510627",
      "name": "Ðô`ng Hô` Thông Minh Apple Watch Series 6 44mm GPS Sport Band",
      "price": "14000000",
      "discount": "",
      "rate": "0",
      "ratecount": "0",
      "sold": "0",
      "instock": "1",
      "location": "B?c Ninh",
      "mall": "Shopee",
      "link": "https://shopee.vn/Ðô`ng Hô` Thông Minh Apple Watch Series 6 44mm GPS Sport Band-i.627563397.15729510627",
      "Model-split": "APPLE WATCH SERIES 6"
    },
    {
      "shopid": "470939058",
      "productid": "11377723982",
      "name": "Ð?ng h? ??PP???? Watch Series 3 b?n LTE ho?t d?ng d?p l?p, Phiên b?n Nhôm 42MM d?p 99% Nhu M?i MRCAU",
      "price": "3350000",
      "discount": "28%",
      "rate": "5",
      "ratecount": "6",
      "sold": "11",
      "instock": "37",
      "location": "TP. H? Chí Minh",
      "mall": "Shopee",
      "link": "https://shopee.vn/Ð?ng h? ??PP???? Watch Series 3 b?n LTE ho?t d?ng d?p l?p, Phiên b?n Nhôm 42MM d?p 99% Nhu M?i MRCAU-i.470939058.11377723982",
      "Color-split": "Ð?NG",
      "Status-split": "99%"
    },
    {
      "shopid": "30166164",
      "productid": "14781778229",
      "name": "táo Watch S6 LTE 40mm",
      "price": "6900000",
      "discount": "",
      "rate": "0",
      "ratecount": "0",
      "sold": "0",
      "instock": "2",
      "location": "Thanh Hóa",
      "mall": "Shopee",
      "link": "https://shopee.vn/táo Watch S6 LTE 40mm-i.30166164.14781778229"
    }
  ]